{
  "id": "smoke_temperature_threshold",
  "title": {
    "en": "Smoke temperature has crossed threshold",
    "nl": "Rooktemperatuur heeft drempelwaarde overschreden",
    "fr": "La température des fumées a traversé le seuil",
    "de": "Rauchtemperatur hat Schwellenwert überschritten",
    "it": "La temperatura dei fumi ha superato la soglia",
    "es": "La temperatura del humo ha cruzado el umbral",
    "sv": "Röktemperatur har korsat tröskelvärdet",
    "no": "Røyktemperatur har krysset terskelverdi",
    "da": "Røgtemperatur har krydset tærskelværdi",
    "ru": "Температура дыма пересекла пороговое значение",
    "pl": "Temperatura dymu przekroczyła próg",
    "ko": "연기 온도가 임계값을 넘었습니다"
  },
  "titleFormatted": {
    "en": "Smoke temperature has [[type]] [[threshold]]",
    "nl": "Rooktemperatuur heeft [[type]] [[threshold]]",
    "fr": "La température des fumées a [[type]] [[threshold]]",
    "de": "Rauchtemperatur hat [[type]] [[threshold]]",
    "it": "La temperatura dei fumi ha [[type]] [[threshold]]",
    "es": "La temperatura del humo ha [[type]] [[threshold]]",
    "sv": "Röktemperatur har [[type]] [[threshold]]",
    "no": "Røyktemperatur har [[type]] [[threshold]]",
    "da": "Røgtemperatur har [[type]] [[threshold]]",
    "ru": "Температура дыма [[type]] [[threshold]]",
    "pl": "Temperatura dymu [[type]] [[threshold]]",
    "ko": "연기 온도가 [[type]] [[threshold]]를 넘었습니다"
  },
  "hint": {
    "en": "Triggered when the smoke temperature crosses a threshold",
    "nl": "Wordt geactiveerd wanneer de rooktemperatuur een drempelwaarde overschrijdt",
    "fr": "Déclenché lorsque la température des fumées franchit un seuil",
    "de": "Wird ausgelöst, wenn die Rauchtemperatur einen Schwellenwert überschreitet",
    "it": "Attivato quando la temperatura dei fumi supera una soglia",
    "es": "Se activa cuando la temperatura del humo cruza un umbral",
    "sv": "Utlöses när röktemperaturen korsar ett tröskelvärde",
    "no": "Utløses når røyktemperaturen krysser en terskelverdi",
    "da": "Udløses når røgtemperaturen krydser en tærskelværdi",
    "ru": "Срабатывает, когда температура дыма пересекает пороговое значение",
    "pl": "Wyzwalane, gdy temperatura dymu przekracza próg",
    "ko": "연기 온도가 임계값을 넘을 때 트리거됩니다"
  },
  "args": [
    {
      "name": "device",
      "type": "device",
      "filter": "driver_id=hottoh"
    },
    {
      "name": "type",
      "type": "dropdown",
      "title": {
        "en": "Direction",
        "nl": "Richting",
        "fr": "Direction",
        "de": "Richtung",
        "it": "Direzione",
        "es": "Dirección",
        "sv": "Riktning",
        "no": "Retning",
        "da": "Retning",
        "ru": "Направление",
        "pl": "Kierunek",
        "ko": "방향"
      },
      "values": [
        {
          "id": "above",
          "title": {
            "en": "has risen above",
            "nl": "is gestegen boven",
            "fr": "a dépassé",
            "de": "ist über",
            "it": "è salita sopra",
            "es": "ha subido por encima",
            "sv": "har stigit över",
            "no": "har steget over",
            "da": "er steget over",
            "ru": "поднялась выше",
            "pl": "wzrosła powyżej",
            "ko": "이상으로 상승"
          }
        },
        {
          "id": "below",
          "title": {
            "en": "has dropped below",
            "nl": "is gedaald onder",
            "fr": "est descendue en dessous de",
            "de": "ist unter",
            "it": "è scesa sotto",
            "es": "ha bajado por debajo",
            "sv": "har sjunkit under",
            "no": "har sunket under",
            "da": "er faldet under",
            "ru": "опустилась ниже",
            "pl": "spadła poniżej",
            "ko": "이하로 하락"
          }
        }
      ]
    },
    {
      "name": "threshold",
      "type": "number",
      "min": 0,
      "max": 300,
      "title": {
        "en": "Temperature",
        "nl": "Temperatuur",
        "fr": "Température",
        "de": "Temperatur",
        "it": "Temperatura",
        "es": "Temperatura",
        "sv": "Temperatur",
        "no": "Temperatur",
        "da": "Temperatur",
        "ru": "Температура",
        "pl": "Temperatura",
        "ko": "온도"
      }
    }
  ],
  "tokens": [
    {
      "name": "temperature",
      "type": "number",
      "title": {
        "en": "Temperature",
        "nl": "Temperatuur",
        "fr": "Température",
        "de": "Temperatur",
        "it": "Temperatura",
        "es": "Temperatura",
        "sv": "Temperatur",
        "no": "Temperatur",
        "da": "Temperatur",
        "ru": "Температура",
        "pl": "Temperatura",
        "ko": "온도"
      },
      "example": 150
    }
  ]
}
