{
  "id": "room_temperature_is",
  "title": {
    "en": "Room temperature is a certain value",
    "nl": "Kamertemperatuur is een bepaalde waarde",
    "fr": "La température ambiante est une certaine valeur",
    "de": "Raumtemperatur ist ein bestimmter Wert",
    "it": "La temperatura ambiente è un certo valore",
    "es": "La temperatura ambiente es un valor determinado",
    "sv": "Rumstemperatur är ett visst värde",
    "no": "Romtemperatur er en bestemt verdi",
    "da": "Rumtemperatur er en bestemt værdi",
    "ru": "Температура в помещении имеет определенное значение",
    "pl": "Temperatura pomieszczenia ma określoną wartość",
    "ko": "실내 온도가 특정 값입니다"
  },
  "titleFormatted": {
    "en": "Room temperature [[comparison]] [[temperature]]",
    "nl": "Kamertemperatuur [[comparison]] [[temperature]]",
    "fr": "La température ambiante [[comparison]] [[temperature]]",
    "de": "Raumtemperatur [[comparison]] [[temperature]]",
    "it": "La temperatura ambiente [[comparison]] [[temperature]]",
    "es": "La temperatura ambiente [[comparison]] [[temperature]]",
    "sv": "Rumstemperatur [[comparison]] [[temperature]]",
    "no": "Romtemperatur [[comparison]] [[temperature]]",
    "da": "Rumtemperatur [[comparison]] [[temperature]]",
    "ru": "Температура в помещении [[comparison]] [[temperature]]",
    "pl": "Temperatura pomieszczenia [[comparison]] [[temperature]]",
    "ko": "실내 온도가 [[comparison]] [[temperature]]"
  },
  "hint": {
    "en": "Check if the room temperature is above/below a certain value",
    "nl": "Controleer of de kamertemperatuur boven/onder een bepaalde waarde ligt",
    "fr": "Vérifiez si la température ambiante est supérieure/inférieure à une certaine valeur",
    "de": "Prüfen, ob die Raumtemperatur über/unter einem bestimmten Wert liegt",
    "it": "Controlla se la temperatura ambiente è sopra/sotto un certo valore",
    "es": "Comprobar si la temperatura ambiente está por encima/debajo de un valor determinado",
    "sv": "Kontrollera om rumstemperaturen är över/under ett visst värde",
    "no": "Sjekk om romtemperaturen er over/under en bestemt verdi",
    "da": "Tjek om rumtemperaturen er over/under en bestemt værdi",
    "ru": "Проверить, находится ли температура в помещении выше/ниже определенного значения",
    "pl": "Sprawdź, czy temperatura pomieszczenia jest powyżej/poniżej określonej wartości",
    "ko": "실내 온도가 특정 값보다 높은지/낮은지 확인합니다"
  },
  "args": [
    {
      "name": "device",
      "type": "device",
      "filter": "driver_id=hottoh"
    },
    {
      "name": "comparison",
      "type": "dropdown",
      "title": {
        "en": "Comparison",
        "nl": "Vergelijking",
        "fr": "Comparaison",
        "de": "Vergleich",
        "it": "Confronto",
        "es": "Comparación",
        "sv": "Jämförelse",
        "no": "Sammenligning",
        "da": "Sammenligning",
        "ru": "Сравнение",
        "pl": "Porównanie",
        "ko": "비교"
      },
      "values": [
        {
          "id": "above",
          "label": {
            "en": "above",
            "nl": "boven",
            "fr": "au-dessus de",
            "de": "über",
            "it": "sopra",
            "es": "por encima de",
            "sv": "över",
            "no": "over",
            "da": "over",
            "ru": "выше",
            "pl": "powyżej",
            "ko": "초과"
          }
        },
        {
          "id": "below",
          "label": {
            "en": "below",
            "nl": "onder",
            "fr": "en dessous de",
            "de": "unter",
            "it": "sotto",
            "es": "por debajo de",
            "sv": "under",
            "no": "under",
            "da": "under",
            "ru": "ниже",
            "pl": "poniżej",
            "ko": "미만"
          }
        },
        {
          "id": "equals",
          "label": {
            "en": "equals",
            "nl": "gelijk aan",
            "fr": "égal à",
            "de": "gleich",
            "it": "uguale a",
            "es": "igual a",
            "sv": "lika med",
            "no": "lik",
            "da": "lig med",
            "ru": "равно",
            "pl": "równe",
            "ko": "같음"
          }
        }
      ]
    },
    {
      "name": "temperature",
      "type": "number",
      "min": 5,
      "max": 35,
      "step": 0.5,
      "title": {
        "en": "Temperature",
        "nl": "Temperatuur",
        "fr": "Température",
        "de": "Temperatur",
        "it": "Temperatura",
        "es": "Temperatura",
        "sv": "Temperatur",
        "no": "Temperatur",
        "da": "Temperatur",
        "ru": "Температура",
        "pl": "Temperatura",
        "ko": "온도"
      }
    }
  ]
}
